natural_query_lib/__init__.py
natural_query_lib/enums.py
natural_query_lib/exceptions.py
natural_query_lib/executor.py
natural_query_lib/query_builder.py
natural_query_lib-0.1.3.dist-info/METADATA
natural_query_lib-0.1.3.dist-info/WHEEL
natural_query_lib-0.1.3.dist-info/licenses/LICENSE.txt
natural_query_lib-0.1.3.dist-info/RECORD
