Metadata-Version: 2.4
Name: natural_query_lib
Version: 0.1.3
Summary: Flexible SQL query builder written in Python! This library allows you to build and execute SQL queries with ease, while supporting dynamic parameters and JSON encoding for database compatibility.
Author-email: Sergio Triana Escobedo <stescobedo.31@gmail.com>
License: MIT License
License-File: LICENSE.txt
Classifier: License :: OSI Approved :: MIT License
Classifier: Operating System :: OS Independent
Classifier: Programming Language :: Python :: 3
Requires-Python: >=3.7
Requires-Dist: asyncpg
